{
  "name": "African Drone and Data Academy (ADDA)",
  "clearOwnership": {
    "isOwnershipExplicit": "Unknown"
  },
  "platformIndependence": {
    "mandatoryDepsCreateMoreRestrictions": "No"
  },
  "documentation": {
    "isDocumentationAvailable": "Unknown"
  },
  "NonPII": {
    "collectsNonPII": "No"
  },
  "privacy": {
    "isPrivacyCompliant": "Unknown"
  },
  "standards": {
    "supportStandards": "Unknown",
    "implementBestPractices": "Unknown"
  },
  "doNoHarm": {
    "preventHarm": {
      "stepsToPreventHarm": "Yes"
    },
    "dataPrivacySecurity": {
      "collectsPII": "Unknown"
    },
    "inappropriateIllegalContent": {
      "collectStoreDistribute": "Yes",
      "type": "Educational content and course material related to the use and application of civilian drones and data management",
      "contentFilter": "Unknown",
      "illegalContentDetection": "Unknown"
    },
    "protectionFromHarassment": {
      "userInteraction": "Yes",
      "addressSafetySecurityUnderageUsers": "Unknown",
      "griefAbuseHarassmentProtection": "Yes",
      "harassmentProtectionSteps": [
        "Code of ethics is shared including stipulations on plagiarism."
      ]
    }
  },
  "locations": {
    "developmentCountries": [
      "United States of America"
    ],
    "deploymentCountries": []
  }
}
