{
  "name": "Platform for Real-time Impact and Situation Monitoring",
  "clearOwnership": {
    "isOwnershipExplicit": "No"
  },
  "platformIndependence": {
    "mandatoryDepsCreateMoreRestrictions": "No"
  },
  "documentation": {
    "isDocumentationAvailable": "Yes",
    "documentationURL": [
      "https://github.com/WFP-VAM/prism-frontend"
    ]
  },
  "NonPII": {
    "collectsNonPII": "No"
  },
  "privacy": {
    "isPrivacyCompliant": "No"
  },
  "standards": {
    "supportStandards": "Yes",
    "standardsList": [
      "https://www.ogc.org/standards/"
    ],
    "implementBestPractices": "Yes",
    "bestPracticesList": [
      "Agile, CD/CI"
    ]
  },
  "doNoHarm": {
    "preventHarm": {
      "stepsToPreventHarm": "Unknown"
    },
    "dataPrivacySecurity": {
      "collectsPII": "No"
    },
    "inappropriateIllegalContent": {
      "collectStoreDistribute": "Yes"
    },
    "protectionFromHarassment": {
      "userInteraction": "No"
    }
  },
  "locations": {
    "developmentCountries": [
      "Indonesia",
      "Cambodia",
      "United States of America",
      "Australia",
      "Italy"
    ],
    "deploymentCountries": [
      "Cambodia",
      "Indonesia",
      "Mongolia"
    ]
  }
}
