{
  "$schema": "http://json-schema.org/draft-07/schema#",
  "$id": "",
  "$comment": "Digital Public Good Metaschema: JSON Schema",
  "title": "Digital Public Good",
  "type": "object",
  "required": [
    "name",
    "description",
    "license",
    "organizations",
    "SDGs",
    "type",
    "stage"
  ],
  "properties": {
    "name": {
      "type": "string",
      "description": "The name of the Digital Public Good. Full name, no initialisms, no acronyms."
    },
    "aliases": {
      "type": "array",
      "description": "Abbreviations, initialisms, or alternate names for Digital Public Good, where relevant.",
      "uniqueItems": true,
      "items": {
        "type": "string"
      }
    },
    "description": {
      "type": "string",
      "description": "Concise 1-line description of Global Digital Public Good"
    },
    "website": {
      "type": "string",
      "description": "Public website for the Global Digital Public Good."
    },
    "license": {
      "type": "array",
      "description": "License(s) under which the Global Digital Pubic Good is released.",
      "minItems": 1,
      "uniqueItems": true,
      "items": {
        "type": "object",
        "required": [
          "spdx",
          "licenseURL"
        ],
        "properties": {
          "spdx": {
            "type": "string",
            "description": "SDPX identifier for this license",
            "enum": [
              "0BSD",
              "AAL",
              "AFL-3.0",
              "AGPL-3.0",
              "Apache-1.1",
              "Apache-2.0",
              "APL-1.0",
              "APSL-2.0",
              "Artistic-1.0",
              "Artistic-2.0",
              "BSD-1-Clause",
              "BSD-2-Clause",
              "BSD-2-Clause-Patent",
              "BSD-3-Clause",
              "BSD-3-Clause-LBNL",
              "BSL-1.0",
              "CAL-1.0",
              "CAL-1.0-Combined-Work-Exception",
              "CATOSL-1.1",
              "CC-BY-1.0",
              "CC-BY-2.0",
              "CC-BY-2.5",
              "CC-BY-3.0",
              "CC-BY-3.0-AT",
              "CC-BY-4.0",
              "CC-BY-NC-1.0",
              "CC-BY-NC-2.0",
              "CC-BY-NC-2.5",
              "CC-BY-NC-3.0",
              "CC-BY-NC-4.0",
              "CC-BY-NC-SA-1.0",
              "CC-BY-NC-SA-2.0",
              "CC-BY-NC-SA-2.5",
              "CC-BY-NC-SA-3.0",
              "CC-BY-NC-SA-4.0",
              "CC-BY-SA-1.0",
              "CC-BY-SA-2.0",
              "CC-BY-SA-2.5",
              "CC-BY-SA-3.0",
              "CC-BY-SA-3.0-AT",
              "CC-BY-SA-4.0",
              "CC0-1.0",
              "CDDL-1.0",
              "CECILL-2.1",
              "CNRI-Python",
              "CPAL-1.0",
              "CPL-1.0",
              "ECL-1.0",
              "ECL-2.0",
              "EFL-1.0",
              "EFL-2.0",
              "Entessa",
              "EPL-1.0",
              "EPL-2.0",
              "EUDatagrid",
              "EUPL-1.2",
              "Fair",
              "Frameworx-1.0",
              "GPL-2.0",
              "GPL-3.0",
              "HPND",
              "IPA",
              "IPL-1.0",
              "ISC",
              "LGPL-2.1",
              "LGPL-3.0",
              "LiLiQ-P-1.1",
              "LiLiQ-R-1.1",
              "LiLiQ-Rplus-1.1",
              "LPL-1.0",
              "LPL-1.02",
              "LPPL-1.3c",
              "MirOS",
              "MIT",
              "MIT-0",
              "Motosoto",
              "MPL-1.0",
              "MPL-1.1",
              "MPL-2.0",
              "MPL-2.0-no-copyleft-exception",
              "MS-PL",
              "MS-RL",
              "MulanPSL-2.0",
              "Multics",
              "NASA-1.3",
              "Naumen",
              "NCSA",
              "NGPL",
              "NLOD-1.0",
              "Nokia",
              "NPOSL-3.0",
              "NTP",
              "OCLC-2.0",
              "ODbL-1.0",
              "ODC-By-1.0 ",
              "OFL-1.1",
              "OFL-1.1-no-RFN",
              "OFL-1.1-RFN",
              "OGTSL",
              "OLDAP-2.8",
              "OSET-PL-2.1",
              "OSL-1.0",
              "OSL-2.1",
              "OSL-3.0",
              "PDDL-1.0",
              "PHP-3.0",
              "PHP-3.01",
              "PostgreSQL",
              "Python-2.0",
              "QPL-1.0",
              "RPL-1.1",
              "RPL-1.5",
              "RPSL-1.0",
              "RSCPL",
              "SimPL-2.0",
              "Sleepycat",
              "SPL-1.0",
              "UCL-1.0",
              "Unicode-DFS-2015",
              "Unicode-DFS-2016",
              "Unlicense",
              "UPL-1.0",
              "VSL-1.0",
              "W3C",
              "Watcom-1.0",
              "Xnet",
              "wxWindows",
              "Zlib",
              "ZPL-2.0"
            ]
          },
          "licenseURL": {
            "type": "string",
            "description": "Link to the license under which the Global Digital Pubic Good is released."
          }
        }
      }
    },
    "SDGs": {
      "type": "array",
      "description": "List of Sustainable Development Goals that this Global Digital Public Good addresses.",
      "minItems": 1,
      "uniqueItems": true,
      "items": {
        "type": "array",
        "enum": [
          [
            1,
            "No Poverty"
          ],
          [
            2,
            "Zero Hunger"
          ],
          [
            3,
            "Good Health and Well-Being"
          ],
          [
            4,
            "Quality Education"
          ],
          [
            5,
            "Gender Equality"
          ],
          [
            6,
            "Clean Water and Sanitation"
          ],
          [
            7,
            "Affordable and Clean Energy"
          ],
          [
            8,
            "Decent Work and Economic Growth"
          ],
          [
            9,
            "Industry, Innovation and Infrastructure"
          ],
          [
            10,
            "Reduced Inequalities"
          ],
          [
            11,
            "Sustainable Cities and Communities"
          ],
          [
            12,
            "Responsible Consumption and Production"
          ],
          [
            13,
            "Climate Action"
          ],
          [
            14,
            "Life Below Water"
          ],
          [
            15,
            "Life On Land"
          ],
          [
            16,
            "Peace, Justice and Strong Institutions"
          ],
          [
            17,
            "Partnerships for the Goals"
          ]
        ]
      }
    },
    "SDGevidence": {
      "type": "string",
      "description": "Relevant links or information to support the relevance to SDGs."
    },
    "sectors": {
      "type": "array",
      "description": "List of sectors that this Global Digital Public Good addresses.",
      "uniqueItems": true,
      "items": {
        "type": "string",
        "enum": [
          "Advocacy",
          "Agriculture",
          "Anti-corruption",
          "Big Data",
          "Business Advocacy",
          "Capacity Development",
          "Centers of Excellence",
          "Civil society",
          "Climate",
          "Communication",
          "Conflict Resolution",
          "Consulting",
          "Corporate Partnerships",
          "Corporation and Business Management",
          "Data Collection",
          "Data Management & Policy",
          "Data Security",
          "Demobilization & Reintegration",
          "Democracy",
          "Development Impact",
          "Digital Development",
          "Digital/Data/Tech",
          "Disarmament",
          "Economics/Finance",
          "Education",
          "Emergency Response",
          "Employment",
          "Energy",
          "Engineering",
          "Enterprise Ecosystems",
          "Entertainment",
          "Environment",
          "Fair & Responsible Media",
          "Female Genital Mutilation",
          "Food",
          "Fragile States",
          "Gender and Minority Groups",
          "Governance",
          "Health",
          "Humanitarian",
          "Hunger",
          "Infrastructure",
          "Justice",
          "Livelihoods",
          "Logistics",
          "Management",
          "Media",
          "Membership Associations",
          "Midwifery",
          "Natural Resource Conflicts",
          "NGO",
          "Nutrition",
          "Peace",
          "Platform creation",
          "Religious Engagement",
          "Research",
          "Resource Management",
          "Security",
          "Social Protection",
          "Stability",
          "Supply Chain Solutions",
          "Sustainability",
          "Sustainable Cities",
          "Training & Employment",
          "Transition",
          "Transparency & Accountability",
          "Travel and Hospitality",
          "Violent Extremism",
          "Water and Sanitation",
          "Workforce",
          "World Population",
          "Youth"
        ]
      }
    },
    "type": {
      "type": "array",
      "description": "List of categories under which this Global Digital Public Good falls into: software, data, standards.",
      "minItems": 1,
      "uniqueItems": true,
      "items": {
        "type": "string",
        "enum": [
          "software",
          "data",
          "content",
          "standard"
        ]
      }
    },
    "repositoryURL": {
      "type": "string",
      "description": "Link to Github (or other) repository"
    },
    "organizations": {
      "type": "array",
      "items": {
        "type": "object",
        "properties": {
          "name": {
            "type": "string",
            "description": "Name of the organization"
          },
          "website": {
            "type": "string",
            "description": "Website of the organization"
          },
          "contact_name": {
            "type": "string",
            "description": "Name of contact individual in the organization"
          },
          "contact_email": {
            "type": "string",
            "description": "Email for contact individual in the organization"
          },
          "org_type": {
            "type": "string",
            "enum": [
              "owner",
              "maintainer",
              "funder",
              "implementer"
            ]
          }
        }
      }
    },
    "stage": {
      "type": "string",
      "enum": [
        "nominee",
        "candidate",
        "DPG"
      ]
    }
  }
}
