{
  "name": "JHSPH OpenCourseware",
  "description": "JHSPH OpenCourseware offers open materials and images from more than a hundred courses developed by the faculty of Johns Hopkins School of Public Health, the world’s foremost institution of public health education and research.",
  "website": "https://ocw.jhsph.edu/",
  "license": [
    {
      "spdx": "CC-BY-NC-SA-2.0",
      "licenseURL": "https://creativecommons.org/licenses/by-nc-sa/2.0/"
    }
  ],
  "SDGs": [
    {
      "SDGNumber": 3
    },
    {
      "SDGNumber": 4
    }
  ],
  "sectors": [],
  "type": [
    "content"
  ],
  "organizations": [
    {
      "name": "Bloomberg School of Public Health, The Johns Hopkins University",
      "website": "https://ocw.jhsph.edu/",
      "org_type": "owner"
    }
  ],
  "stage": "nominee"
}
