{
  "name": "Alex",
  "description": "Catch insensitive, inconsiderate writing",
  "website": "",
  "license": [
    {
      "spdx": "MIT",
      "licenseURL": "https://github.com/get-alex/alex/blob/master/license"
    }
  ],
  "SDGs": [
    {
      "SDGNumber": 11
    }
  ],
  "sectors": [],
  "type": [
    "software"
  ],
  "repositories": [
    {
      "name": "main",
      "url": "https://github.com/get-alex/alex"
    }
  ],
  "organizations": [
    {
      "name": "Alex",
      "website": "https://alexjs.com/",
      "org_type": "owner"
    }
  ],
  "stage": "archive"
}
