{
  "name": "BEMServer",
  "description": "An open source Python server to deploy energy management solutions for buildings",
  "website": "https://bemserver.org/",
  "license": [
    {
      "spdx": "AGPL-3.0",
      "licenseURL": "https://github.com/HIT2GAP-EU-PROJECT/bemserver/blob/master/LICENSE"
    }
  ],
  "SDGs": [
    {
      "SDGNumber": 7,
      "evidenceURL": "https://cordis.europa.eu/article/id/418007-middleware-system-utilises-ai-to-coordinate-building-energy-management"
    },
    {
      "SDGNumber": 11,
      "evidenceURL": "https://cordis.europa.eu/article/id/418007-middleware-system-utilises-ai-to-coordinate-building-energy-management"
    }
  ],
  "sectors": [],
  "type": [
    "software"
  ],
  "repositories": [
    {
      "name": "main",
      "url": "https://github.com/HIT2GAP-EU-PROJECT/bemserver"
    }
  ],
  "organizations": [
    {
      "name": "HIT2GAP",
      "website": "https://smartcities-infosystem.eu/sites-projects/projects/hit2gap",
      "org_type": "owner"
    }
  ],
  "stage": "nominee"
}
